audiorename/__init__.py
audiorename/args.py
audiorename/audiofile.py
audiorename/batch.py
audiorename/example-config.ini
audiorename/job.py
audiorename/message.py
audiorename/meta.py
audiorename/musicbrainz.py
audiorename/utils.py
audiorename-4.0.0.dist-info/LICENSE
audiorename-4.0.0.dist-info/METADATA
audiorename-4.0.0.dist-info/WHEEL
audiorename-4.0.0.dist-info/entry_points.txt
audiorename-4.0.0.dist-info/RECORD
