Metadata-Version: 2.1
Name: audiorename
Version: 4.0.0
Summary: Rename audio files from metadata tags.
Home-page: https://github.com/Josef-Friedrich/audiorename
License: MIT
Author: Josef Friedrich
Author-email: josef@friedrich.rocks
Requires-Python: >=3.9,<=3.13
Classifier: Development Status :: 5 - Production/Stable
Classifier: License :: OSI Approved :: MIT License
Classifier: Programming Language :: Python
Classifier: Programming Language :: Python :: 3
Classifier: Programming Language :: Python :: 3.9
Classifier: Programming Language :: Python :: 3.10
Classifier: Programming Language :: Python :: 3.11
Classifier: Programming Language :: Python :: 3.12
Classifier: Programming Language :: Python :: 3.13
Requires-Dist: ansicolor (>=0,<1)
Requires-Dist: musicbrainzngs (>=0,<1)
Requires-Dist: phrydy (>=4,<5)
Requires-Dist: tmep (>=2,<3)
Project-URL: Repository, https://github.com/Josef-Friedrich/audiorename
